openapipages/__about__.py
openapipages/__init__.py
openapipages/base.py
openapipages/elements.py
openapipages/py.typed
openapipages/rapidoc.py
openapipages/redoc.py
openapipages/scalar.py
openapipages/swaggerui.py
openapipages-0.2.1.dist-info/METADATA
openapipages-0.2.1.dist-info/WHEEL
openapipages-0.2.1.dist-info/licenses/LICENSE
openapipages-0.2.1.dist-info/RECORD
