Metadata-Version: 2.4
Name: openapipages
Version: 0.2.1
Summary: OpenAPI Spec-based pages (SwaggerUI, ReDoc, RapiDoc, Elements, Scalar) ready with configuration features.
Project-URL: changelog, https://github.com/hasansezertasan/openapipages/blob/main/CHANGELOG.md
Project-URL: documentation, https://github.com/hasansezertasan/openapipages#readme
Project-URL: homepage, https://github.com/hasansezertasan/openapipages
Project-URL: issues, https://github.com/hasansezertasan/openapipages/issues
Project-URL: releasenotes, https://github.com/hasansezertasan/openapipages/releases
Project-URL: source, https://github.com/hasansezertasan/openapipages.git
Author-email: Hasan Sezer Taşan <hasansezertasan@gmail.com>
Maintainer-email: Hasan Sezer Taşan <hasansezertasan@gmail.com>
License-Expression: MIT
License-File: LICENSE
Keywords: api,documentation,elements,fastapi,flask,litestar,openapi,openapipages,rapidoc,redoc,scalar,spec,specification,swagger,swagger-ui
Classifier: Development Status :: 4 - Beta
Classifier: Environment :: Web Environment
Classifier: Framework :: FastAPI
Classifier: Framework :: Flask
Classifier: Intended Audience :: Developers
Classifier: Intended Audience :: Information Technology
Classifier: License :: OSI Approved :: MIT License
Classifier: Operating System :: OS Independent
Classifier: Programming Language :: Python
Classifier: Programming Language :: Python :: 3 :: Only
Classifier: Programming Language :: Python :: 3.8
Classifier: Programming Language :: Python :: 3.9
Classifier: Programming Language :: Python :: 3.10
Classifier: Programming Language :: Python :: 3.11
Classifier: Programming Language :: Python :: 3.12
Classifier: Programming Language :: Python :: 3.13
Classifier: Programming Language :: Python :: Implementation :: CPython
Classifier: Programming Language :: Python :: Implementation :: PyPy
Classifier: Topic :: Internet
Classifier: Topic :: Internet :: WWW/HTTP
Classifier: Topic :: Internet :: WWW/HTTP :: HTTP Servers
Classifier: Topic :: Software Development
Classifier: Topic :: Software Development :: Libraries
Classifier: Topic :: Software Development :: Libraries :: Application Frameworks
Classifier: Topic :: Software Development :: Libraries :: Python Modules
Classifier: Typing :: Typed
Requires-Python: >=3.8
